dataclass_sqlalchemy_mixins/__init__.py
dataclass_sqlalchemy_mixins/base/__init__.py
dataclass_sqlalchemy_mixins/base/mixins.py
dataclass_sqlalchemy_mixins/base/utils.py
dataclass_sqlalchemy_mixins/pydantic_mixins/__init__.py
dataclass_sqlalchemy_mixins/pydantic_mixins/sqlalchemy_base_models.py
dataclass_sqlalchemy_mixins-0.3.4.dist-info/LICENSE
dataclass_sqlalchemy_mixins-0.3.4.dist-info/METADATA
dataclass_sqlalchemy_mixins-0.3.4.dist-info/WHEEL
dataclass_sqlalchemy_mixins-0.3.4.dist-info/RECORD
