Metadata-Version: 2.1
Name: dataclass-sqlalchemy-mixins
Version: 0.3.4
Summary: Allows to convert dataclasses to sqlalchemy filters and orderings.
Author: ViAchKoN
Requires-Python: >=3.8.1,<4.0.0
Classifier: License :: OSI Approved :: MIT License
Classifier: Operating System :: OS Independent
Classifier: Programming Language :: Python :: 3
Classifier: Programming Language :: Python :: 3.9
Classifier: Programming Language :: Python :: 3.10
Classifier: Programming Language :: Python :: 3.11
Classifier: Programming Language :: Python :: 3.12
Provides-Extra: pydantic
Requires-Dist: pydantic (>=1.9) ; extra == "pydantic"
Requires-Dist: sqlalchemy (>=1.4.2)
